MANIFEST.in
README.md
bunnyducky.py
ducktools.py
setup.py
ducktoolkit/__init__.py
ducktoolkit/common.py
ducktoolkit/decoder.py
ducktoolkit/encoder.py
ducktoolkit.egg-info/PKG-INFO
ducktoolkit.egg-info/SOURCES.txt
ducktoolkit.egg-info/dependency_links.txt
ducktoolkit.egg-info/not-zip-safe
ducktoolkit.egg-info/top_level.txt
ducktoolkit/languages/be.json
ducktoolkit/languages/br.json
ducktoolkit/languages/ca.json
ducktoolkit/languages/ch.json
ducktoolkit/languages/de.json
ducktoolkit/languages/dk.json
ducktoolkit/languages/es.json
ducktoolkit/languages/fi.json
ducktoolkit/languages/fr.json
ducktoolkit/languages/gb.json
ducktoolkit/languages/hr.json
ducktoolkit/languages/it.json
ducktoolkit/languages/no.json
ducktoolkit/languages/pt.json
ducktoolkit/languages/se.json
ducktoolkit/languages/si.json
ducktoolkit/languages/us.json