Metadata-Version: 2.1
Name: ducktoolkit
Version: 1.0.3
Summary: USB Rubber Ducky Toolkit
Home-page: https://ducktoolkit.com
Author: Kevin Breen, James Hall
Author-email: pip@ducktoolkit.com
License: GNU V3
Platform: UNKNOWN
